{
  "id": "2-11545282-5",
  "page_title": "Utah Jazz all-time roster",
  "section_title": "E",
  "caption": "E",
  "doc": {
    "id": "2-11545282-5",
    "rows": [
      [
        "Mark Eaton",
        "United States",
        "Center",
        "1982-94",
        "UCLA"
      ],
      [
        "Jerry Eaves",
        "United States",
        "Guard",
        "1982-84",
        "Louisville"
      ],
      [
        "Blue Edwards",
        "United States",
        "Guard",
        "1989-92; 1994-95",
        "East Carolina"
      ],
      [
        "Howard Eisley",
        "United States",
        "Guard",
        "1995-2000, 2004-05",
        "Boston College"
      ],
      [
        "Francisco Elson",
        "Netherlands",
        "Center",
        "2010-11",
        "California"
      ],
      [
        "Jeremy Evans",
        "United States",
        "Forward",
        "2010-present",
        "Western Kentucky"
      ]
    ],
    "types": [
      "text",
      "text",
      "text",
      "text",
      "text"
    ],
    "header": [
      "Player",
      "Nationality",
      "Position",
      "Years for Jazz",
      "School/Club Team"
    ],
    "caption": "E",
    "page_id": 11545282,
    "page_title": "Utah Jazz all-time roster",
    "section_title": "E"
  }
}